[{"name":"metadata.json","path":"dist/metadata.json","internal_type":35,"type":"Metadata"},{"name":"hitch","path":"dist/hitch_linux_arm64_v8.0/hitch","goos":"linux","goarch":"arm64","goarm64":"v8.0","target":"linux_arm64_v8.0","internal_type":4,"type":"Binary","extra":{"Binary":"hitch","Builder":"go","Ext":"","ID":"hitch"}},{"name":"hitch","path":"dist/hitch_linux_amd64_v1/hitch","goos":"linux","goarch":"amd64","goamd64":"v1","target":"linux_amd64_v1","internal_type":4,"type":"Binary","extra":{"Binary":"hitch","Builder":"go","Ext":"","ID":"hitch"}},{"name":"hitch.exe","path":"dist/hitch_windows_amd64_v1/hitch.exe","goos":"windows","goarch":"amd64","goamd64":"v1","target":"windows_amd64_v1","internal_type":4,"type":"Binary","extra":{"Binary":"hitch","Builder":"go","Ext":".exe","ID":"hitch"}},{"name":"hitch","path":"dist/hitch_darwin_arm64_v8.0/hitch","goos":"darwin","goarch":"arm64","goarm64":"v8.0","target":"darwin_arm64_v8.0","internal_type":4,"type":"Binary","extra":{"Binary":"hitch","Builder":"go","Ext":"","ID":"hitch"}},{"name":"hitch","path":"dist/hitch_darwin_amd64_v1/hitch","goos":"darwin","goarch":"amd64","goamd64":"v1","target":"darwin_amd64_v1","internal_type":4,"type":"Binary","extra":{"Binary":"hitch","Builder":"go","Ext":"","ID":"hitch"}},{"name":"hitch_0.0.1-next_darwin_arm64.tar.gz","path":"dist/hitch_0.0.1-next_darwin_arm64.tar.gz","goos":"darwin","goarch":"arm64","goarm64":"v8.0","target":"darwin_arm64_v8.0","internal_type":1,"type":"Archive","extra":{"Binaries":["hitch"],"Checksum":"sha256:ad01ac61536c57df264a0aee2d77958d33d3c3a188b0134f245f155b97b896b1","Format":"tar.gz","ID":"default","WrappedIn":""}},{"name":"hitch_0.0.1-next_windows_amd64.zip","path":"dist/hitch_0.0.1-next_windows_amd64.zip","goos":"windows","goarch":"amd64","goamd64":"v1","target":"windows_amd64_v1","internal_type":1,"type":"Archive","extra":{"Binaries":["hitch.exe"],"Checksum":"sha256:6cdcc2758f3e54322ef3b71e85fabc666a6ca693044cfcc315bca585722c44c9","Format":"zip","ID":"default","WrappedIn":""}},{"name":"hitch_0.0.1-next_linux_arm64.tar.gz","path":"dist/hitch_0.0.1-next_linux_arm64.tar.gz","goos":"linux","goarch":"arm64","goarm64":"v8.0","target":"linux_arm64_v8.0","internal_type":1,"type":"Archive","extra":{"Binaries":["hitch"],"Checksum":"sha256:029f4e12d9ddda5a568c1df15ddc1cf2683ad26241ba452617ee7c15e4d5dfc6","Format":"tar.gz","ID":"default","WrappedIn":""}},{"name":"hitch_0.0.1-next_darwin_amd64.tar.gz","path":"dist/hitch_0.0.1-next_darwin_amd64.tar.gz","goos":"darwin","goarch":"amd64","goamd64":"v1","target":"darwin_amd64_v1","internal_type":1,"type":"Archive","extra":{"Binaries":["hitch"],"Checksum":"sha256:09ce95441dd600bfb884c9cebc31f89fe5c922ef7253e9f4a2049e4f194ce326","Format":"tar.gz","ID":"default","WrappedIn":""}},{"name":"hitch_0.0.1-next_linux_amd64.tar.gz","path":"dist/hitch_0.0.1-next_linux_amd64.tar.gz","goos":"linux","goarch":"amd64","goamd64":"v1","target":"linux_amd64_v1","internal_type":1,"type":"Archive","extra":{"Binaries":["hitch"],"Checksum":"sha256:8ae99acb375320611b62e9847953636c7d03fc8a743630601bc5697463d7f678","Format":"tar.gz","ID":"default","WrappedIn":""}},{"name":"checksums.txt","path":"dist/checksums.txt","internal_type":12,"type":"Checksum","extra":{}},{"name":"hitch.rb","path":"dist/homebrew/Formula/hitch.rb","internal_type":16,"type":"Homebrew Formula","extra":{"BrewConfig":{"name":"hitch","repository":{"owner":"DoomedRamen","name":"hitch","branch":"homebrew","git":{},"pull_request":{"base":{}}},"commit_author":{"name":"goreleaserbot","email":"bot@goreleaser.com","signing":{}},"commit_msg_template":"Brew formula update for {{ .ProjectName }} version {{ .Tag }}","directory":"Formula","install":"bin.install \"hitch\"\n\n# Install shell completions (if we add them later)\n# bash_completion.install \"completions/hitch.bash\" =\u003e \"hitch\"\n# zsh_completion.install \"completions/_hitch\" =\u003e \"_hitch\"\n# fish_completion.install \"completions/hitch.fish\"\n","test":"system \"#{bin}/hitch\", \"--version\"\n","description":"Git workflow manager for multi-environment development teams","homepage":"https://github.com/DoomedRamen/hitch","license":"MIT","goarm":"6","goamd64":"v1"}}}]